tensorspark/__init__.py
tensorspark/MNIST_data/t10k-images-idx1-ubyte
tensorspark/MNIST_data/t10k-labels-idx1-ubyte
tensorspark/MNIST_data/train-images-idx1-ubyte
tensorspark/MNIST_data/train-labels-idx1-ubyte
tensorspark/core/__init__.py
tensorspark/core/hdfs_util.py
tensorspark/core/httpfs_util.py
tensorspark/core/param_server.py
tensorspark/core/partitioner.py
tensorspark/core/session_util.py
tensorspark/core/session_worker.py
tensorspark/core/spark_session.py
tensorspark/core/weight_combiner.py
tensorspark/example/__init__.py
tensorspark/example/mnist.py
tensorspark/example/spark_mnist.py
tensorspark/test/__init__.py
tensorspark/test/test_combiner.py
tensorspark/test/test_hdfs.py
tensorspark/test/test_tensorflow.py
tensorspark/test/test_tornado.py
tensorspark-1.0.6.dist-info/DESCRIPTION.rst
tensorspark-1.0.6.dist-info/METADATA
tensorspark-1.0.6.dist-info/RECORD
tensorspark-1.0.6.dist-info/WHEEL
tensorspark-1.0.6.dist-info/metadata.json
tensorspark-1.0.6.dist-info/top_level.txt
