Metadata-Version: 2.0
Name: tensorspark
Version: 1.0.6
Summary: Tensorflow on Spark, a scalable system for high-performance machine learning
Home-page: https://github.com/liangfengsid/tensoronspark/
Author: Liang Feng
Author-email: loengf@connect.hku.hk
License: Apache
Platform: UNKNOWN
Classifier: Development Status :: 4 - Beta
Classifier: Topic :: System :: Distributed Computing
Classifier: Topic :: Scientific/Engineering :: Artificial Intelligence
Classifier: License :: OSI Approved :: Apache Software License
Classifier: Programming Language :: Python :: 2.7
Classifier: Operating System :: POSIX :: Linux
Classifier: Operating System :: Unix
Classifier: Environment :: Console
